options/__init__.py
options/admin.py
options/apps.py
options/constants.py
options/context_processors.py
options/helpers.py
options/management/__init__.py
options/management/commands/__init__.py
options/management/commands/export_options.py
options/managers.py
options/migrations/0001_initial.py
options/migrations/0002_auto_20181002_0254.py
options/migrations/0003_auto_20190827_0605.py
options/migrations/0004_auto_20190829_0936.py
options/migrations/0005_option_help_text_useroption_help_text.py
options/migrations/__init__.py
options/models.py
options/rest_framework/permissions.py
options/rest_framework/serializers.py
options/rest_framework/viewsets.py
options/settings.py
django_simple_options-2.4.0.dist-info/LICENSE
django_simple_options-2.4.0.dist-info/METADATA
django_simple_options-2.4.0.dist-info/WHEEL
django_simple_options-2.4.0.dist-info/RECORD
