Metadata-Version: 2.1
Name: django-simple-options
Version: 2.4.0
Summary: Simple app to add configuration options to a Django project.
Home-page: https://github.com/marcosgabarda/django-simple-options
License: MIT
Author: Marcos Gabarda
Author-email: hey@marcosgabarda.com
Requires-Python: >=3.10,<4.0
Classifier: Environment :: Web Environment
Classifier: Framework :: Django
Classifier: License :: OSI Approved :: MIT License
Classifier: Programming Language :: Python :: 3
Classifier: Programming Language :: Python :: 3.10
Classifier: Programming Language :: Python :: 3.11
Requires-Dist: django (>=3.0.0)
Requires-Dist: djangorestframework (>=3.11.0)
